trendly/__init__.py
trendly/sources/__init__.py
trendly/sources/twitter.py
trendly-0.1.0.dist-info/WHEEL
trendly-0.1.0.dist-info/METADATA
trendly-0.1.0.dist-info/RECORD
