Metadata-Version: 2.1
Name: trendly
Version: 0.1.0
Summary: Real time trend analysis
Author: jonirap
Requires-Python: >=3.10,<4.0
Classifier: Programming Language :: Python :: 3
Classifier: Programming Language :: Python :: 3.10
Requires-Dist: searchtweets-v2 (>=1.1.1,<2.0.0)
